dwellpy/__init__.py
dwellpy/main.py
dwellpy/config/__init__.py
dwellpy/config/constants.py
dwellpy/core/__init__.py
dwellpy/core/click_manager.py
dwellpy/core/dwell_algorithm.py
dwellpy/core/input_manager.py
dwellpy/dwellpy/__init__.py
dwellpy/dwellpy/__version__.py
dwellpy/dwellpy/main.py
dwellpy/managers/__init__.py
dwellpy/managers/button_manager.py
dwellpy/managers/exit_manager.py
dwellpy/managers/settings_manager.py
dwellpy/managers/ui_manager.py
dwellpy/managers/window_manager.py
dwellpy/ui/click_feedback.py
dwellpy/ui/scroll_widget.py
dwellpy/ui/ui_manager.py
dwellpy/ui/window_manager.py
dwellpy/ui/dialogs/__init__.py
dwellpy/ui/dialogs/exit_dialog.py
dwellpy/ui/dialogs/settings_dialog.py
dwellpy/utils/__init__.py
dwellpy/utils/helpers.py
dwellpy/utils/logging_config.py
dwellpy-0.7.1.dist-info/licenses/LICENSE
dwellpy-0.7.1.dist-info/METADATA
dwellpy-0.7.1.dist-info/WHEEL
dwellpy-0.7.1.dist-info/entry_points.txt
dwellpy-0.7.1.dist-info/top_level.txt
dwellpy-0.7.1.dist-info/RECORD
