Metadata-Version: 2.4
Name: dwellpy
Version: 0.7.1
Summary: Accessibility dwell clicker for motor disabilities
Author: code0nwheels
License: GPL-3.0
Project-URL: Homepage, https://github.com/code0nwheels/dwellpy
Project-URL: Documentation, https://github.com/code0nwheels/dwellpy/wiki
Project-URL: Repository, https://github.com/code0nwheels/dwellpy
Project-URL: Bug Reports, https://github.com/code0nwheels/dwellpy/issues
Keywords: accessibility,dwell,clicker,motor,disabilities,assistive,technology
Classifier: Development Status :: 4 - Beta
Classifier: Intended Audience :: End Users/Desktop
Classifier: License :: OSI Approved :: GNU General Public License v3 (GPLv3)
Classifier: Operating System :: OS Independent
Classifier: Programming Language :: Python :: 3
Classifier: Programming Language :: Python :: 3.9
Classifier: Programming Language :: Python :: 3.10
Classifier: Programming Language :: Python :: 3.11
Classifier: Programming Language :: Python :: 3.12
Classifier: Programming Language :: Python :: 3.13
Classifier: Topic :: Desktop Environment :: Window Managers
Classifier: Topic :: Adaptive Technologies
Requires-Python: >=3.9
License-File: LICENSE
Requires-Dist: PyQt6>=6.4.0
Requires-Dist: pynput>=1.7.6
Dynamic: license-file
